README.md
setup.cfg
setup.py
cloudgenix_get_prisma/__init__.py
cloudgenix_get_prisma/gpcloudservice.py
cloudgenix_get_prisma.egg-info/PKG-INFO
cloudgenix_get_prisma.egg-info/SOURCES.txt
cloudgenix_get_prisma.egg-info/dependency_links.txt
cloudgenix_get_prisma.egg-info/entry_points.txt
cloudgenix_get_prisma.egg-info/requires.txt
cloudgenix_get_prisma.egg-info/top_level.txt