Metadata-Version: 2.1
Name: cloudgenix-get-prisma
Version: 1.0.3
Summary: Utility to print or export all CloudGenix ServiceLinks to Prisma.
Home-page: https://github.com/ebob9/cloudgenix_get_prisma
Author: Aaron Edwards
Author-email: cloudgenix_get_prisma@ebob9.com
License: MIT
Platform: UNKNOWN
Classifier: Development Status :: 5 - Production/Stable
Classifier: Intended Audience :: Developers
Classifier: License :: OSI Approved :: MIT License
Classifier: Programming Language :: Python :: 3.7
Classifier: Programming Language :: Python :: 3.8
Classifier: Programming Language :: Python :: 3.9
